bonk_bot/__init__.py
bonk_bot/avatar.py
bonk_bot/bonk_maps.py
bonk_bot/bonk_online.py
bonk_bot/dbids.json
bonk_bot/friend_list.py
bonk_bot/game.py
bonk_bot/room.py
bonk_bot/settings.py
bonk_bot/bot/__init__.py
bonk_bot/bot/bonk_bot.py
bonk_bot/bot/bot_event_handler.py
bonk_bot/parsers/__init__.py
bonk_bot/parsers/byte_buffer.py
bonk_bot/parsers/parsers.py
bonk_bot/types/__init__.py
bonk_bot/types/game_inputs.py
bonk_bot/types/modes.py
bonk_bot/types/servers.py
bonk_bot/types/teams.py
bonk_bot-2.0.4.dist-info/LICENSE
bonk_bot-2.0.4.dist-info/METADATA
bonk_bot-2.0.4.dist-info/WHEEL
bonk_bot-2.0.4.dist-info/top_level.txt
bonk_bot-2.0.4.dist-info/RECORD
