Metadata-Version: 2.1
Name: bonk_bot
Version: 2.0.4
Summary: Python API wrapper for bonk.io web game.
Author: Safizapi
Maintainer: Safizapi
License: MIT License
Project-URL: Repository, https://github.com/Safizapi/bonk_bot
Keywords: bonk,bonk.io,bots,api,bonk-bot
Classifier: Development Status :: 4 - Beta
Classifier: Intended Audience :: Developers
Classifier: License :: OSI Approved :: MIT License
Classifier: Programming Language :: Python :: 3.8
Classifier: Programming Language :: Python :: 3.9
Classifier: Programming Language :: Python :: 3.10
Classifier: Programming Language :: Python :: 3.11
Classifier: Programming Language :: Python :: 3.12
Requires-Python: >=3.8
License-File: LICENSE
Requires-Dist: python-engineio ==3.14.2
Requires-Dist: python-socketio ==4.6.0
Requires-Dist: aiohttp ==3.9.5
Requires-Dist: requests ==2.32.3
Requires-Dist: nest-asyncio ==1.6.0
Requires-Dist: pymitter ==0.5.1
Requires-Dist: lzstring ==1.0.4
Requires-Dist: setuptools ==70.1.0
